dj_templated_mail/__init__.py
dj_templated_mail/admin.py
dj_templated_mail/logic.py
dj_templated_mail/models.py
dj_templated_mail-0.1.3.dist-info/DESCRIPTION.rst
dj_templated_mail-0.1.3.dist-info/METADATA
dj_templated_mail-0.1.3.dist-info/metadata.json
dj_templated_mail-0.1.3.dist-info/RECORD
dj_templated_mail-0.1.3.dist-info/top_level.txt
dj_templated_mail-0.1.3.dist-info/WHEEL
