Metadata-Version: 2.0
Name: dj-templated-mail
Version: 0.1.3
Summary: Django app that provides possibility to render email messages from templates stored in DB.
Home-page: https://github.com/oeegor/dj-templated-mail#django-templated-mail/
Author: Egor Orlov
Author-email: oeegor@gmail.com
License: MIT License
Platform: any
Classifier: Environment :: Web Environment
Classifier: Framework :: Django
Classifier: Intended Audience :: Developers
Classifier: License :: OSI Approved :: MIT License
Classifier: Operating System :: OS Independent
Classifier: Programming Language :: Python
Classifier: Programming Language :: Python :: 2.5
Classifier: Programming Language :: Python :: 2.6
Classifier: Programming Language :: Python :: 2.7
Classifier: Programming Language :: Python :: 3
Classifier: Programming Language :: Python :: 3.2
Classifier: Programming Language :: Python :: 3.3
Classifier: Topic :: Internet :: WWW/HTTP
Classifier: Topic :: Internet :: WWW/HTTP :: Dynamic Content
